[
  {
    "review_id": "9834300",
    "movie_id": "93717",
    "author": "ksho****",
    "review": "정말 한국드라마중에 제대로 된 드라마였다. 배우 캐스팅부터 몰입도까지... 30대 이상이라면 정말 더 공감갈수 있는 드라마였다. 최고의 드라마였다!!!",
    "rating": "10",
    "date": "15.04.08"
  },
  {
    "review_id": "7953181",
    "movie_id": "93717",
    "author": "yuno****",
    "review": "명작^^",
    "rating": "10",
    "date": "13.09.06"
  },
  {
    "review_id": "7029833",
    "movie_id": "93717",
    "author": "kesk****",
    "review": "화려한 캐스팅 배우들의 연기력도 좋았지만 아쉬운점이라면 종편에서는 높은 시청률이었기에   지나친 연장 방송으로 질질 끌었음.. 한국드라마의 고질적인 문제. 연장만 안했어도 명작이 될수 있었을텐데...",
    "rating": "7",
    "date": "12.12.22"
  },
  {
    "review_id": "6994869",
    "movie_id": "93717",
    "author": "odjs****",
    "review": "배우들의 캐스팅도 좋고 내용도 매우 재밌는 드라마.",
    "rating": "10",
    "date": "12.12.12"
  },
  {
    "review_id": "6471593",
    "movie_id": "93717",
    "author": "juri****",
    "review": "부모님이 더 우시는 드라마 ㅠ.ㅠ",
    "rating": "10",
    "date": "12.07.12"
  },
  {
    "review_id": "6450596",
    "movie_id": "93717",
    "author": "dlsg****",
    "review": "ㅠㅠㅠㅠ이게진짜드라마지",
    "rating": "10",
    "date": "12.07.06"
  },
  {
    "review_id": "6335204",
    "movie_id": "93717",
    "author": "tmdf****",
    "review": "꽤 슬프다.",
    "rating": "10",
    "date": "12.05.26"
  }
]